PyECCArithmetic/__init__.py
PyECCArithmetic/curve.py
PyECCArithmetic/error.py
PyECCArithmetic/point.py
PyECCArithmetic-1.1.0.dist-info/LICENSE
PyECCArithmetic-1.1.0.dist-info/METADATA
PyECCArithmetic-1.1.0.dist-info/WHEEL
PyECCArithmetic-1.1.0.dist-info/top_level.txt
PyECCArithmetic-1.1.0.dist-info/RECORD
