Metadata-Version: 2.1
Name: PyECCArithmetic
Version: 1.1.0
Summary: Basic arithmetic operations for points on elliptic curves.
Home-page: https://github.com/Kavakuo/PyECCArithmetic
Author: Philipp Nieting
Author-email: developer@nieting.de
License: UNKNOWN
Platform: UNKNOWN
Classifier: Programming Language :: Python :: 3
Classifier: License :: OSI Approved :: MIT License
Classifier: Operating System :: OS Independent
Classifier: Intended Audience :: Developers
Classifier: Intended Audience :: Education
Classifier: Topic :: Security :: Cryptography
Requires-Python: >=3.0
